eeapp/__init__.py
eeapp/location_migrate.py
eeapp/manage.py
eeapp/base/__init__.py
eeapp/base/admin.py
eeapp/base/apps.py
eeapp/base/models.py
eeapp/base/urls.py
eeapp/base/views.py
eeapp/base/api/__init__.py
eeapp/base/api/serializer.py
eeapp/base/api/urls.py
eeapp/base/api/views.py
eeapp/base/fields/ImageSetField.py
eeapp/base/fields/__init__.py
eeapp/base/migrations/__init__.py
eeapp/base/model/Images.py
eeapp/base/model/__init__.py
eeapp/eeapp/__init__.py
eeapp/eeapp/settings.py
eeapp/eeapp/urls.py
eeapp/eeapp/wsgi.py
eeapp/jsonapi/__init__.py
eeapp/jsonapi/authentication.py
eeapp/jsonapi/authentications.py
eeapp/jsonapi/crawl.py
eeapp/jsonapi/exception.py
eeapp/jsonapi/response.py
eeapp/jsonapi/views.py
eeapp/location/__init__.py
eeapp/location/admin.py
eeapp/location/apps.py
eeapp/location/models.py
eeapp/location/tests.py
eeapp/location/views.py
eeapp/location/api/__init__.py
eeapp/location/api/auth.py
eeapp/location/api/serializer.py
eeapp/location/api/urls.py
eeapp/location/api/views.py
eeapp/location/migrations/0001_initial.py
eeapp/location/migrations/__init__.py
eeapp/rest/__init__.py
eeapp/rest/crossdomain.py
eeapp/rest/exception.py
eeapp/rest/response.py
eeapp/rest/view/__init__.py
eeapp/rest/view/authView.py
eeapp/tools/__init__.py
eeapp/tools/database_router.py
eeapp/tools/datasrouter.py
eeapp/tools/db/__init__.py
eeapp/tools/db/models.py
eeapp/wxsupport/__init__.py
eeapp/wxsupport/admin.py
eeapp/wxsupport/apps.py
eeapp/wxsupport/models.py
eeapp/wxsupport/tests.py
eeapp/wxsupport/views.py
eeapp/wxsupport/wxsign.py
eeapp/wxsupport/migrations/__init__.py
eeapp-0.0.62.dist-info/LICENSE
eeapp-0.0.62.dist-info/METADATA
eeapp-0.0.62.dist-info/WHEEL
eeapp-0.0.62.dist-info/top_level.txt
eeapp-0.0.62.dist-info/RECORD
