Metadata-Version: 2.1
Name: eeapp
Version: 0.0.62
Summary: A small example packcage add tools
Home-page: https://github.com/pypa/example-project
Author: zhuxietong
Author-email: zhuxietong@me.com
License: UNKNOWN
Platform: UNKNOWN
Classifier: Programming Language :: Python :: 3
Classifier: License :: OSI Approved :: MIT License
Classifier: Operating System :: OS Independent
Requires-Dist: django
Requires-Dist: djangorestframework
Requires-Dist: six
Requires-Dist: Pillow
